[
  {
    "query": "bangladesh cyclone",
    "paper": "dailyObserver",
    "date_range": [
      "1/1/2014",
      "12/31/2014"
    ],
    "sites": [
      "https://www.observerbd.com/2014/10/03/46973.php",
      "https://www.observerbd.com/2014/11/08/53280.php",
      "https://www.observerbd.com/2014/10/03/46792.php",
      "https://www.observerbd.com/2014/10/12/48297.php",
      "https://www.observerbd.com/2014/10/15/48845.php",
      "https://www.observerbd.com/2014/10/12/48159.php",
      "https://www.observerbd.com/2014/10/12/48309.php",
      "https://www.observerbd.com/2014/10/14/48572.php",
      "https://www.observerbd.com/2014/10/12/48235.php",
      "https://www.observerbd.com/2014/10/03/46982.php",
      "https://www.observerbd.com/2014/10/14/48501.php",
      "https://www.observerbd.com/2014/10/09/47544.php",
      "https://www.observerbd.com/2014/10/12/48083.php",
      "https://www.observerbd.com/2014/10/13/48354.php",
      "https://www.observerbd.com/2014/10/15/48783.php",
      "https://www.observerbd.com/2014/10/15/48703.php",
      "https://www.observerbd.com/2014/10/15/48831.php",
      "https://www.observerbd.com/2014/10/09/47653.php",
      "https://www.observerbd.com/2014/10/03/46980.php",
      "https://www.observerbd.com/2014/10/14/48500.php",
      "https://www.observerbd.com/2014/11/08/53262.php",
      "https://www.observerbd.com/2014/10/13/48465.php"
    ]
  },
  {
    "query": "bangladesh cyclone",
    "paper": "dailyObserver",
    "date_range": [
      "1/1/2015",
      "12/31/2015"
    ],
    "sites": [
      "https://www.observerbd.com/2015/04/30/86327.php",
      "https://www.observerbd.com/2015/02/28/75112.php",
      "https://www.observerbd.com/2015/07/30/101997.php",
      "https://www.observerbd.com/2015/07/30/101970.php",
      "https://www.observerbd.com/2015/07/30/101960.php",
      "https://www.observerbd.com/2015/11/14/120720.php",
      "https://www.observerbd.com/2015/07/29/101791.php",
      "https://www.observerbd.com/2015/10/02/113115.php"
    ]
  },
  {
    "query": "bangladesh cyclone",
    "paper": "dailyObserver",
    "date_range": [
      "1/1/2016",
      "12/31/2016"
    ],
    "sites": [
      "https://www.observerbd.com/2016/05/21/152576.php",
      "https://www.observerbd.com/2016/05/26/153281.php",
      "https://www.observerbd.com/2016/05/27/153250.php",
      "https://www.observerbd.com/2016/05/26/153160.php",
      "https://www.observerbd.com/2016/05/26/153145.php",
      "https://www.observerbd.com/2016/05/20/152289.php",
      "https://www.observerbd.com/2016/05/21/152432.php",
      "https://www.observerbd.com/2016/05/25/152958.php",
      "https://www.observerbd.com/2016/05/25/153008.php",
      "https://www.observerbd.com/2016/05/21/152522.php",
      "https://www.observerbd.com/2016/05/27/153252.php",
      "https://www.observerbd.com/2016/05/24/152765.php",
      "https://www.observerbd.com/2016/05/27/153253.php",
      "https://www.observerbd.com/2016/05/25/152939.php",
      "https://www.observerbd.com/2016/05/26/153068.php",
      "https://www.observerbd.com/2016/05/26/153108.php",
      "https://www.observerbd.com/2016/05/22/152698.php",
      "https://www.observerbd.com/2016/05/27/153301.php"
    ]
  },
  {
    "query": "bangladesh cyclone",
    "paper": "dailyObserver",
    "date_range": [
      "1/1/2017",
      "12/31/2017"
    ],
    "sites": [
      "https://www.observerbd.com/author.php?n=Mamunur-Rashid",
      "http://www.observerbd.com/details.php?id=72468",
      "http://www.observerbd.com/author.php?n=Md%20Abdus%20Sobhan",
      "http://www.observerbd.com/author.php?n=Shah%20Jalal",
      "https://www.observerbd.com/details.php?id=70728"
    ]
  },
  {
    "query": "bangladesh cyclone",
    "paper": "dailyObserver",
    "date_range": [
      "1/1/2018",
      "12/31/2018"
    ],
    "sites": [
      "https://www.observerbd.com/details.php?id=117276",
      "http://www.observerbd.com/details.php?id=137250",
      "https://www.observerbd.com/cat.php?cd=193",
      "https://www.observerbd.com/cat.php?cd=186",
      "https://www.observerbd.com/video.php?pg=10&vid=y3niFzo5VLI",
      "https://www.observerbd.com/cat.php?cd=199",
      "https://www.observerbd.com/cat.php?cd=191",
      "https://www.observerbd.com/cat.php?cd=194",
      "https://www.observerbd.com/cat.php?cd=215",
      "http://www.observerbd.com/author.php?n=Rana%20Dutta",
      "http://www.observerbd.com/visual.php?id=52",
      "https://www.observerbd.com/details.php?id=142449",
      "https://www.observerbd.com/details.php?id=150610",
      "https://www.observerbd.com/details.php?id=116806",
      "http://www.observerbd.com/details.php?id=160186",
      "https://www.observerbd.com/details.php?id=130486",
      "https://www.observerbd.com/details.php?id=165572"
    ]
  },
  {
    "query": "bangladesh cyclone",
    "paper": "dailyObserver",
    "date_range": [
      "1/1/2019",
      "12/31/2019"
    ],
    "sites": [
      "https://www.observerbd.com/details.php?id=196124",
      "https://www.observerbd.com/details.php?id=196137",
      "https://www.observerbd.com/details.php?id=195988",
      "https://www.observerbd.com/details.php?id=228546",
      "https://www.observerbd.com/details.php?id=223091",
      "http://www.observerbd.com/details.php?id=187383",
      "https://www.observerbd.com/details.php?id=195740",
      "https://www.observerbd.com/details.php?id=227540",
      "http://www.observerbd.com/details.php?id=191580",
      "https://www.observerbd.com/details.php?id=179720",
      "https://www.observerbd.com/details.php?id=178026",
      "https://www.observerbd.com/details.php?id=219592",
      "https://www.observerbd.com/details.php?id=201951",
      "http://www.observerbd.com/details.php?id=188691",
      "https://www.observerbd.com/details.php?id=194682",
      "https://www.observerbd.com/details.php?id=234299",
      "https://www.observerbd.com/details.php?id=228814",
      "https://www.observerbd.com/details.php?id=190982",
      "https://www.observerbd.com/details.php?id=204458",
      "http://www.observerbd.com/details.php?id=179995",
      "https://www.observerbd.com/details.php?id=212643",
      "https://www.observerbd.com/details.php?id=202397",
      "https://www.observerbd.com/details.php?id=189344",
      "https://www.observerbd.com/details.php?id=208799",
      "https://www.observerbd.com/details.php?id=234093",
      "https://www.observerbd.com/details.php?id=190746",
      "http://www.observerbd.com/details.php?id=181940",
      "https://www.observerbd.com/details.php?id=228966",
      "https://www.observerbd.com/details.php?id=214034",
      "http://www.observerbd.com/details.php?id=182320",
      "https://www.observerbd.com/details.php?id=209798",
      "https://www.observerbd.com/details.php?id=233248",
      "https://www.observerbd.com/details.php?id=199926",
      "https://www.observerbd.com/details.php?id=218022",
      "https://www.observerbd.com/details.php?id=185264",
      "https://www.observerbd.com/details.php?id=215046",
      "https://www.observerbd.com/details.php?id=195862",
      "https://www.observerbd.com/details.php?id=215739",
      "https://www.observerbd.com/details.php?id=207521",
      "https://www.observerbd.com/details.php?id=183295",
      "https://www.observerbd.com/details.php?id=194205",
      "http://www.observerbd.com/details.php?id=182902",
      "https://www.observerbd.com/details.php?id=236106",
      "https://www.observerbd.com/details.php?id=190345",
      "https://www.observerbd.com/details.php?id=209120",
      "http://www.observerbd.com/details.php?id=187700",
      "https://www.observerbd.com/details.php?id=231234",
      "http://www.observerbd.com/details.php?id=184847",
      "http://www.observerbd.com/details.php?id=177683",
      "https://www.observerbd.com/details.php?id=221752",
      "https://www.observerbd.com/details.php?id=219750",
      "https://www.observerbd.com/details.php?id=234270",
      "https://www.observerbd.com/details.php?id=197840",
      "https://www.observerbd.com/details.php?id=226766",
      "https://www.observerbd.com/details.php?id=185757",
      "https://www.observerbd.com/details.php?id=217965",
      "https://www.observerbd.com/details.php?id=215626",
      "https://www.observerbd.com/details.php?id=186594",
      "https://www.observerbd.com/details.php?id=226985",
      "https://www.observerbd.com/details.php?id=217046",
      "https://www.observerbd.com/details.php?id=218330",
      "https://www.observerbd.com/details.php?id=204505",
      "https://www.observerbd.com/details.php?id=192728",
      "https://www.observerbd.com/details.php?id=209879",
      "https://www.observerbd.com/details.php?id=200779",
      "https://www.observerbd.com/details.php?id=206444",
      "https://www.observerbd.com/details.php?id=193122",
      "https://www.observerbd.com/details.php?id=228665",
      "https://www.observerbd.com/details.php?id=227933",
      "https://www.observerbd.com/details.php?id=219925",
      "http://www.observerbd.com/details.php?id=182890",
      "https://www.observerbd.com/details.php?id=205644",
      "https://www.observerbd.com/details.php?id=182935",
      "https://www.observerbd.com/details.php?id=232138",
      "https://www.observerbd.com/details.php?id=228334",
      "https://www.observerbd.com/details.php?id=199753",
      "http://www.observerbd.com/details.php?id=184154",
      "https://www.observerbd.com/details.php?id=215428",
      "https://www.observerbd.com/details.php?id=206001",
      "https://www.observerbd.com/details.php?id=210622",
      "http://www.observerbd.com/details.php?id=179993",
      "https://www.observerbd.com/details.php?id=186093",
      "https://www.observerbd.com/details.php?id=228023",
      "https://www.observerbd.com/details.php?id=217002",
      "https://www.observerbd.com/details.php?id=222761",
      "https://www.observerbd.com/details.php?id=216808",
      "https://www.observerbd.com/details.php?id=222921",
      "https://www.observerbd.com/details.php?id=195021",
      "https://www.observerbd.com/details.php?id=202965",
      "https://www.observerbd.com/details.php?id=208550",
      "https://www.observerbd.com/details.php?id=230418",
      "https://www.observerbd.com/details.php?id=206980",
      "https://www.observerbd.com/details.php?id=226114",
      "https://www.observerbd.com/details.php?id=189926",
      "https://www.observerbd.com/details.php?id=194551",
      "https://www.observerbd.com/details.php?id=220623",
      "http://www.observerbd.com/details.php?id=183815",
      "https://www.observerbd.com/details.php?id=216494",
      "https://www.observerbd.com/details.php?id=201368",
      "https://www.observerbd.com/details.php?id=232425",
      "https://www.observerbd.com/details.php?id=219932",
      "https://www.observerbd.com/details.php?id=203608",
      "https://www.observerbd.com/details.php?id=228473",
      "https://www.observerbd.com/details.php?id=212498",
      "https://www.observerbd.com/details.php?id=228448",
      "https://www.observerbd.com/details.php?id=232617",
      "https://www.observerbd.com/details.php?id=215898",
      "https://www.observerbd.com/details.php?id=227351",
      "https://www.observerbd.com/details.php?id=195004",
      "https://www.observerbd.com/details.php?id=196853",
      "https://www.observerbd.com/details.php?id=191356",
      "http://www.observerbd.com/details.php?id=183260",
      "https://www.observerbd.com/details.php?id=220352",
      "https://www.observerbd.com/details.php?id=193544",
      "http://www.observerbd.com/details.php?id=190264",
      "http://www.observerbd.com/details.php?id=189002",
      "https://www.observerbd.com/details.php?id=190511",
      "https://www.observerbd.com/details.php?id=180943",
      "https://www.observerbd.com/details.php?id=227671",
      "https://www.observerbd.com/details.php?id=228317",
      "https://www.observerbd.com/details.php?id=193309",
      "https://www.observerbd.com/details.php?id=205682",
      "http://www.observerbd.com/details.php?id=177686",
      "https://www.observerbd.com/details.php?id=232464",
      "https://www.observerbd.com/details.php?id=226992",
      "https://www.observerbd.com/details.php?id=235939",
      "https://www.observerbd.com/details.php?id=215335",
      "https://www.observerbd.com/details.php?id=232738",
      "https://www.observerbd.com/details.php?id=186718",
      "https://www.observerbd.com/details.php?id=196992",
      "https://www.observerbd.com/details.php?id=196619",
      "https://www.observerbd.com/details.php?id=227383",
      "http://www.observerbd.com/details.php?id=189513",
      "https://www.observerbd.com/details.php?id=205822",
      "http://www.observerbd.com/details.php?id=180959",
      "https://www.observerbd.com/details.php?id=215744",
      "https://www.observerbd.com/details.php?id=187340",
      "https://www.observerbd.com/details.php?id=196759",
      "https://www.observerbd.com/details.php?id=230426",
      "http://www.observerbd.com/details.php?id=225224",
      "https://www.observerbd.com/details.php?id=225072",
      "https://www.observerbd.com/details.php?id=222808",
      "https://www.observerbd.com/details.php?id=193524",
      "https://www.observerbd.com/details.php?id=228282",
      "https://www.observerbd.com/details.php?id=207465",
      "https://www.observerbd.com/details.php?id=196417",
      "https://www.observerbd.com/details.php?id=199058",
      "http://www.observerbd.com/details.php?id=189626",
      "http://www.observerbd.com/details.php?id=187161",
      "https://www.observerbd.com/details.php?id=214100",
      "https://www.observerbd.com/details.php?id=210284",
      "https://www.observerbd.com/details.php?id=235630",
      "https://www.observerbd.com/details.php?id=208579",
      "https://www.observerbd.com/details.php?id=185263",
      "https://www.observerbd.com/details.php?id=192487",
      "https://www.observerbd.com/details.php?id=230626",
      "http://www.observerbd.com/details.php?id=186312",
      "https://www.observerbd.com/details.php?id=218246",
      "https://www.observerbd.com/details.php?id=190988",
      "https://www.observerbd.com/details.php?id=217784",
      "https://www.observerbd.com/details.php?id=212299",
      "https://www.observerbd.com/details.php?id=211306",
      "https://www.observerbd.com/details.php?id=222130",
      "https://www.observerbd.com/details.php?id=220751",
      "https://www.observerbd.com/details.php?id=234592",
      "https://www.observerbd.com/details.php?id=191886",
      "https://www.observerbd.com/details.php?id=217833",
      "https://www.observerbd.com/details.php?id=176625",
      "http://www.observerbd.com/details.php?id=183262",
      "http://www.observerbd.com/details.php?id=230626",
      "https://www.observerbd.com/details.php?id=183480",
      "https://www.observerbd.com/details.php?id=190095",
      "https://www.observerbd.com/details.php?id=232784",
      "https://www.observerbd.com/details.php?id=218141",
      "https://www.observerbd.com/details.php?id=198090",
      "https://www.observerbd.com/details.php?id=191894",
      "https://www.observerbd.com/details.php?id=201502",
      "https://www.observerbd.com/details.php?id=214713",
      "https://www.observerbd.com/details.php?id=198321",
      "https://www.observerbd.com/details.php?id=217054",
      "https://www.observerbd.com/details.php?id=227297",
      "https://www.observerbd.com/details.php?id=215429",
      "https://www.observerbd.com/details.php?id=226429",
      "https://www.observerbd.com/details.php?id=181043",
      "https://www.observerbd.com/details.php?id=230250",
      "https://www.observerbd.com/details.php?id=204031",
      "http://www.observerbd.com/details.php?id=184328",
      "https://www.observerbd.com/details.php?id=196813",
      "https://www.observerbd.com/details.php?id=209603",
      "https://www.observerbd.com/details.php?id=181742",
      "https://www.observerbd.com/details.php?id=208560",
      "https://www.observerbd.com/details.php?id=195002",
      "https://www.observerbd.com/details.php?id=197885",
      "https://www.observerbd.com/cat.php?cd=209",
      "https://www.observerbd.com/details.php?id=197169",
      "https://www.observerbd.com/details.php?id=215255",
      "https://www.observerbd.com/details.php?id=219430",
      "https://www.observerbd.com/details.php?id=228577",
      "https://www.observerbd.com/details.php?id=234831",
      "https://www.observerbd.com/details.php?id=195978",
      "https://www.observerbd.com/details.php?id=203156",
      "https://www.observerbd.com/details.php?id=218541",
      "https://www.observerbd.com/details.php?id=214498",
      "https://www.observerbd.com/details.php?id=204569",
      "https://www.observerbd.com/details.php?id=232291",
      "https://www.observerbd.com/details.php?id=194150",
      "http://www.observerbd.com/details.php?id=182230",
      "https://www.observerbd.com/details.php?id=197125",
      "http://www.observerbd.com/details.php?id=178610",
      "https://www.observerbd.com/details.php?id=215969",
      "https://www.observerbd.com/details.php?id=182438",
      "https://www.observerbd.com/details.php?id=208358",
      "https://www.observerbd.com/details.php?id=182261",
      "https://www.observerbd.com/details.php?id=207787",
      "https://www.observerbd.com/details.php?id=194878",
      "https://www.observerbd.com/details.php?id=177721",
      "https://www.observerbd.com/details.php?id=236156",
      "https://www.observerbd.com/details.php?id=208596",
      "https://www.observerbd.com/details.php?id=189536",
      "https://www.observerbd.com/details.php?id=219053",
      "https://www.observerbd.com/details.php?id=218269",
      "https://www.observerbd.com/details.php?id=223903",
      "https://www.observerbd.com/details.php?id=205465",
      "https://www.observerbd.com/details.php?id=223515",
      "https://www.observerbd.com/details.php?id=198644",
      "https://www.observerbd.com/details.php?id=221318",
      "http://www.observerbd.com/details.php?id=185389",
      "https://www.observerbd.com/details.php?id=226633",
      "https://www.observerbd.com/details.php?id=180014",
      "https://www.observerbd.com/details.php?id=231114",
      "https://www.observerbd.com/details.php?id=205478",
      "https://www.observerbd.com/details.php?id=190846",
      "https://www.observerbd.com/details.php?id=208389",
      "https://www.observerbd.com/details.php?id=202273",
      "https://www.observerbd.com/details.php?id=224830",
      "https://www.observerbd.com/details.php?id=203114",
      "https://www.observerbd.com/details.php?id=183688",
      "https://www.observerbd.com/details.php?id=194263",
      "https://www.observerbd.com/details.php?id=227996",
      "https://www.observerbd.com/details.php?id=231462",
      "https://www.observerbd.com/details.php?id=176523",
      "https://www.observerbd.com/details.php?id=204172",
      "https://www.observerbd.com/details.php?id=212543",
      "https://www.observerbd.com/details.php?id=225397",
      "https://www.observerbd.com/details.php?id=233557",
      "https://www.observerbd.com/details.php?id=224827",
      "https://www.observerbd.com/details.php?id=217618",
      "https://www.observerbd.com/details.php?id=228609",
      "https://www.observerbd.com/details.php?id=228255",
      "https://www.observerbd.com/details.php?id=192002",
      "https://www.observerbd.com/details.php?id=232508",
      "https://www.observerbd.com/details.php?id=213770",
      "https://www.observerbd.com/details.php?id=204571",
      "https://www.observerbd.com/details.php?id=190232",
      "https://www.observerbd.com/details.php?id=211783",
      "https://www.observerbd.com/details.php?id=229418",
      "https://www.observerbd.com/details.php?id=209407",
      "https://www.observerbd.com/news.php?id=233608",
      "https://www.observerbd.com/details.php?id=197514",
      "https://www.observerbd.com/details.php?id=224439",
      "https://www.observerbd.com/details.php?id=232504",
      "http://www.observerbd.com/details.php?id=187384",
      "https://www.observerbd.com/details.php?id=188531",
      "https://www.observerbd.com/details.php?id=198007",
      "https://www.observerbd.com/details.php?id=214958",
      "https://www.observerbd.com/details.php?id=220823",
      "http://www.observerbd.com/details.php?id=182783",
      "https://www.observerbd.com/details.php?id=210798",
      "https://www.observerbd.com/details.php?id=217490",
      "https://www.observerbd.com/details.php?id=195705",
      "https://www.observerbd.com/details.php?id=224921",
      "https://www.observerbd.com/details.php?id=192162",
      "https://www.observerbd.com/details.php?id=235662",
      "https://www.observerbd.com/details.php?id=228677",
      "https://www.observerbd.com/details.php?id=192667",
      "https://www.observerbd.com/details.php?id=187583",
      "https://www.observerbd.com/details.php?id=219412",
      "https://www.observerbd.com/details.php?id=228623",
      "https://www.observerbd.com/details.php?id=220586",
      "https://www.observerbd.com/details.php?id=190577",
      "http://www.observerbd.com/details.php?id=178203",
      "https://www.observerbd.com/details.php?id=204328",
      "https://www.observerbd.com/details.php?id=212209",
      "https://www.observerbd.com/details.php?id=213725",
      "https://www.observerbd.com/details.php?id=223816",
      "https://www.observerbd.com/details.php?id=199919",
      "https://www.observerbd.com/details.php?id=225364",
      "http://www.observerbd.com/details.php?id=186856",
      "https://www.observerbd.com/details.php?id=196119",
      "https://www.observerbd.com/details.php?id=229695",
      "https://www.observerbd.com/details.php?id=202845",
      "https://www.observerbd.com/details.php?id=206975",
      "https://www.observerbd.com/details.php?id=234514",
      "https://www.observerbd.com/details.php?id=218104",
      "https://www.observerbd.com/details.php?id=229659",
      "https://www.observerbd.com/details.php?id=191416",
      "https://www.observerbd.com/details.php?id=198950",
      "https://www.observerbd.com/details.php?id=229696",
      "https://www.observerbd.com/details.php?id=224115",
      "https://www.observerbd.com/details.php?id=228458"
    ]
  }
]