[
  {
    "query": "bangladesh floods",
    "paper": "dailyObserver",
    "date_range": [
      "1/1/2014",
      "12/31/2014"
    ],
    "sites": [
      "https://www.observerbd.com/2014/09/06/41457.php",
      "https://www.observerbd.com/2014/11/03/52462.php",
      "https://www.observerbd.com/2014/09/21/44395.php",
      "https://www.observerbd.com/2014/09/22/44597.php",
      "https://www.observerbd.com/2014/11/25/56824.php"
    ]
  },
  {
    "query": "bangladesh floods",
    "paper": "dailyObserver",
    "date_range": [
      "1/1/2015",
      "12/31/2015"
    ],
    "sites": [
      "https://www.observerbd.com/2015/08/01/102284.php",
      "https://www.observerbd.com/2015/07/29/101865.php",
      "https://www.observerbd.com/2015/08/01/102479.php",
      "https://www.observerbd.com/2015/08/01/102323.php",
      "https://www.observerbd.com/2015/02/17/73044.php",
      "https://www.observerbd.com/2015/09/10/109790.php",
      "https://www.observerbd.com/2015/05/18/89448.php",
      "https://www.observerbd.com/2015/10/17/115864.php",
      "https://www.observerbd.com/2015/02/07/71110.php",
      "https://www.observerbd.com/2015/10/24/117001.php",
      "https://www.observerbd.com/2015/07/29/101902.php",
      "https://www.observerbd.com/2015/08/01/102431.php",
      "https://www.observerbd.com/2015/07/22/100525.php",
      "https://www.observerbd.com/2015/08/01/102327.php",
      "https://www.observerbd.com/2015/01/04/64557.php",
      "https://www.observerbd.com/2015/07/29/101803.php",
      "https://www.observerbd.com/2015/06/23/95749.php",
      "https://www.observerbd.com/2015/07/29/101791.php",
      "https://www.observerbd.com/2015/09/05/108942.php",
      "https://www.observerbd.com/2015/09/10/109787.php",
      "https://www.observerbd.com/2015/01/27/68892.php",
      "https://www.observerbd.com/2015/08/01/102313.php",
      "https://www.observerbd.com/2015/05/18/89293.php",
      "https://www.observerbd.com/2015/08/01/102393.php",
      "https://www.observerbd.com/2015/09/10/109786.php"
    ]
  },
  {
    "query": "bangladesh floods",
    "paper": "dailyObserver",
    "date_range": [
      "1/1/2016",
      "12/31/2016"
    ],
    "sites": [
      "https://www.observerbd.com/2016/06/28/158548.php",
      "https://www.observerbd.com/2016/06/25/158051.php",
      "https://www.observerbd.com/2016/04/24/148158.php",
      "https://www.observerbd.com/2016/06/25/158045.php",
      "https://www.observerbd.com/2016/04/24/148118.php",
      "https://www.observerbd.com/2016/06/25/158109.php",
      "https://www.observerbd.com/2016/04/24/148109.php",
      "https://www.observerbd.com/2016/06/25/158108.php",
      "https://www.observerbd.com/2016/06/25/158068.php"
    ]
  },
  {
    "query": "bangladesh floods",
    "paper": "dailyObserver",
    "date_range": [
      "1/1/2017",
      "12/31/2017"
    ],
    "sites": [
      "http://www.observerbd.com/details.php?id=72468",
      "http://www.observerbd.com/details.php?id=95465",
      "http://www.observerbd.com/details.php?id=84078",
      "http://www.observerbd.com/author.php?n=Md%20Abdus%20Sobhan"
    ]
  },
  {
    "query": "bangladesh floods",
    "paper": "dailyObserver",
    "date_range": [
      "1/1/2018",
      "12/31/2018"
    ],
    "sites": [
      "https://www.observerbd.com/details.php?id=168933",
      "https://www.observerbd.com/details.php?id=148703",
      "https://www.observerbd.com/cat.php?cd=199",
      "https://www.observerbd.com/details.php?id=137428",
      "https://www.observerbd.com/details.php?id=135888",
      "https://www.observerbd.com/video.php?pg=9&vid=e695qBTGr14",
      "https://www.observerbd.com/details.php?id=175045"
    ]
  },
  {
    "query": "bangladesh floods",
    "paper": "dailyObserver",
    "date_range": [
      "1/1/2019",
      "12/31/2019"
    ],
    "sites": [
      "https://www.observerbd.com/details.php?id=230110",
      "https://www.observerbd.com/details.php?id=207936",
      "https://www.observerbd.com/details.php?id=219756",
      "http://www.observerbd.com/details.php?id=187460",
      "https://www.observerbd.com/details.php?id=223565",
      "https://www.observerbd.com/details.php?id=195421",
      "https://www.observerbd.com/details.php?id=196124",
      "https://www.observerbd.com/details.php?id=195002",
      "https://www.observerbd.com/details.php?id=190988",
      "https://www.observerbd.com/details.php?id=189536",
      "https://www.observerbd.com/details.php?id=213328",
      "https://www.observerbd.com/details.php?id=220352",
      "http://www.observerbd.com/details.php?id=186856",
      "http://www.observerbd.com/details.php?id=183512",
      "https://www.observerbd.com/details.php?id=211854",
      "https://www.observerbd.com/details.php?id=205083",
      "https://www.observerbd.com/gallery.php?pg=59",
      "https://www.observerbd.com/gallery.php?pg=98",
      "https://www.observerbd.com/details.php?id=229415",
      "https://www.observerbd.com/details.php?id=189394",
      "http://www.observerbd.com/details.php?id=182230",
      "https://www.observerbd.com/details.php?id=198901",
      "https://www.observerbd.com/details.php?id=185642",
      "https://www.observerbd.com/details.php?id=188542",
      "https://www.observerbd.com/details.php?id=201951",
      "https://www.observerbd.com/cat.php?cd=187",
      "https://www.observerbd.com/details.php?id=208249",
      "https://www.observerbd.com/details.php?id=224175",
      "https://www.observerbd.com/details.php?id=182438",
      "http://www.observerbd.com/details.php?id=181784",
      "https://www.observerbd.com/details.php?id=193356",
      "https://www.observerbd.com/details.php?id=198474",
      "https://www.observerbd.com/details.php?id=228966",
      "https://www.observerbd.com/details.php?id=191498",
      "https://www.observerbd.com/details.php?id=191532",
      "https://www.observerbd.com/details.php?id=219355",
      "https://www.observerbd.com/details.php?id=233838",
      "https://www.observerbd.com/details.php?id=183688"
    ]
  }
]