{
  "annotatable": {
    "parts": [
      "s1v1"
    ]
  },
  "anncomplete": true,
  "sources": [],
  "metas": {
    "m_33": {
      "value": false,
      "confidence": {
        "state": "pre-added",
        "who": [
          "user:shammun"
        ],
        "prob": 1
      }
    },
    "m_57": {
      "value": false,
      "confidence": {
        "state": "pre-added",
        "who": [
          "user:shammun"
        ],
        "prob": 1
      }
    },
    "m_55": {
      "value": false,
      "confidence": {
        "state": "pre-added",
        "who": [
          "user:shammun"
        ],
        "prob": 1
      }
    },
    "m_28": {
      "value": false,
      "confidence": {
        "state": "pre-added",
        "who": [
          "user:shammun"
        ],
        "prob": 1
      }
    },
    "m_30": {
      "value": "dhaka_tribune",
      "confidence": {
        "state": "pre-added",
        "who": [
          "user:shammun"
        ],
        "prob": 1
      }
    }
  },
  "entities": [],
  "relations": [],
  "filename": "dhakaTribune_data_ec5964b4-54e1-4cbe-97dc-9174a70e5e76.txt",
  "text": "Date Published:2020-04-17 00:00:00      \nMore than 70 coronavirus vaccines are in development globally - with three drugmakers already running trials and a fourth vaccine candidate about to start phase I clinical trials   "
}